{
  "updatedAt": "2026-07-09T14:05:57.853Z",
  "categories": {
    "memes": [],
    "bnb": [
      {
        "name": "Trusty AI",
        "symbol": "Trusty",
        "assetId": "0x65aea108c21439693468FCD542D81C29E8df4444",
        "chain": "bsc",
        "priceUsd": 0.00003813,
        "marketCapUsd": 38133,
        "priceChange24h": -3.96,
        "volume24h": 295.73,
        "liquidity": 21316.95,
        "logoUrl": "https://cdn.dexscreener.com/cms/images/X-shg1fyEiyjZ92z?width=800&height=800&quality=95&format=auto",
        "pairAddress": "0xe2D86D6dFDE0D428f8F83260b6C7c1e7f16C8ed2",
        "pinned": true
      }
    ],
    "eth": [],
    "sol": [
      {
        "name": "Only Possible On Solana",
        "symbol": "OPOS",
        "assetId": "BqVHWpwUDgMik5gbTciFfozadpE2oZth5bxCDrgbDt52",
        "chain": "solana",
        "priceUsd": 596.051,
        "marketCapUsd": 462181808,
        "priceChange24h": 495911,
        "volume24h": 9122194.76,
        "liquidity": 9823721.97,
        "logoUrl": null,
        "pairAddress": "5vVxnXb1XDVUwE82bx5PSZFbEssYqmM5wS9uMzd2kfM2"
      },
      {
        "name": "AVAJAK",
        "symbol": "AVAJAK",
        "assetId": "HnkB6cP2fEZE6KwdHwLEdEEDT8J5kUGPL1wFRqd4pump",
        "chain": "solana",
        "priceUsd": 0.0008181,
        "marketCapUsd": 818122,
        "priceChange24h": 2478,
        "volume24h": 2809231.71,
        "liquidity": 74882.87,
        "logoUrl": "https://cdn.dexscreener.com/cms/images/0dzMqxxKFiR3qB6m?width=800&height=800&quality=95&format=auto",
        "pairAddress": "CW3K643XAzZFLHTUyGKdq1Zx2eTeTTnu4bUs73WhaZc5"
      },
      {
        "name": "EVERMEADOW",
        "symbol": "EVERMEADOW",
        "assetId": "31mMFCFe3V5tx319s5kNfnPrYCzc8SuxPofGcyfepump",
        "chain": "solana",
        "priceUsd": 0.0006708,
        "marketCapUsd": 670830,
        "priceChange24h": 1802,
        "volume24h": 1766184.78,
        "liquidity": 65236.98,
        "logoUrl": "https://cdn.dexscreener.com/cms/images/6eMhtAHNwj5dan8Q?width=800&height=800&quality=95&format=auto",
        "pairAddress": "AfZmaLhPhZYx6YRmJhhdzV5fSVKy5a4Qox55MQXicMfi"
      },
      {
        "name": "Only Possible On Solana",
        "symbol": "OPOS",
        "assetId": "DvnY3MgpmpWeZTLJSsoCsk3pwpYJ79bjNgxreBttpump",
        "chain": "solana",
        "priceUsd": 0.0001243,
        "marketCapUsd": 124341,
        "priceChange24h": 289,
        "volume24h": 760714.41,
        "liquidity": 27454.08,
        "logoUrl": "https://cdn.dexscreener.com/cms/images/OIB0Aw80X9MBJ03E?width=800&height=800&quality=95&format=auto",
        "pairAddress": "HWhsKtrmfKDPjRC114HKAyz4LKWW1LRSKJop9ai83Ghn"
      },
      {
        "name": "fatcat",
        "symbol": "fatcat",
        "assetId": "G8bNZABJLB6A1iKyuQdJWXGtgo6UxwQ2DC7gZXWQpump",
        "chain": "solana",
        "priceUsd": 0.00009799,
        "marketCapUsd": 97720,
        "priceChange24h": 212,
        "volume24h": 1871996.7,
        "liquidity": 26459.86,
        "logoUrl": "https://cdn.dexscreener.com/cms/images/V5WTaIlRx4kjzPak?width=800&height=800&quality=95&format=auto",
        "pairAddress": "ecMLugdZenwkrb3hcBRdPyPvFUMV9ZxfhVoMBRJHtAK"
      },
      {
        "name": "ARROW",
        "symbol": "ARROW",
        "assetId": "G6cHLEwYHyZJXBhKpSWMU6RUtcq9HM9UTn2cTEdKpump",
        "chain": "solana",
        "priceUsd": 0.0001001,
        "marketCapUsd": 100114,
        "priceChange24h": 153,
        "volume24h": 1275406.63,
        "liquidity": 25015.85,
        "logoUrl": "https://cdn.dexscreener.com/cms/images/j1ARADbMVPoPDu77?width=800&height=800&quality=95&format=auto",
        "pairAddress": "2kgp6eoGqJUEvXTmMmMow45syg3mBvq9TdLXc34uJJ9M"
      },
      {
        "name": "bro the cat",
        "symbol": "bro",
        "assetId": "ArEvdUzDBrxd6WZZZyV7zMemwij65M6JfAFF9PuPpump",
        "chain": "solana",
        "priceUsd": 0.00007522,
        "marketCapUsd": 75227,
        "priceChange24h": 109,
        "volume24h": 268520.03,
        "liquidity": 20908.96,
        "logoUrl": "https://cdn.dexscreener.com/cms/images/B0nV5BjDaU87Am-J?width=800&height=800&quality=95&format=auto",
        "pairAddress": "BbMCA8UmaBjbEhUiiUx1modzgKVCCckY5fMseFxyQCow"
      },
      {
        "name": "NIGGABULL",
        "symbol": "NIGGABULL",
        "assetId": "77x1fCskDLaiZmm2uZKEhARSCD2B86VaahTkK2Vfpump",
        "chain": "solana",
        "priceUsd": 0.001113,
        "marketCapUsd": 1113615,
        "priceChange24h": 51.42,
        "volume24h": 903274.62,
        "liquidity": 88624.15,
        "logoUrl": "https://cdn.dexscreener.com/cms/images/EFfwoTPIz2eqlIQM?width=800&height=800&quality=95&format=auto",
        "pairAddress": "985nRFKE9yHRwmPVPW7GCje1Jr7WtDdnyzb4QCNZEq15"
      },
      {
        "name": "the bleck bull",
        "symbol": "ANSUM",
        "assetId": "GaZb3DE2U3Jcjx7ddAVwobsBKnCaDoJWLbzTvJYhpump",
        "chain": "solana",
        "priceUsd": 0.0007286,
        "marketCapUsd": 728501,
        "priceChange24h": 25.45,
        "volume24h": 323551.55,
        "liquidity": 77350.87,
        "logoUrl": "https://cdn.dexscreener.com/cms/images/ju5nj3-7sial9oFW?width=800&height=800&quality=95&format=auto",
        "pairAddress": "3jEQBiQCWSABEGEmAPFJfr8UEbhfNT7wVEDAcDyuJ1oL"
      },
      {
        "name": "Free Joby",
        "symbol": "Joby",
        "assetId": "4SnKwnz6DyagftnFqdxsvWvehrcbEDhxmmXNQk2Jpump",
        "chain": "solana",
        "priceUsd": 0.003247,
        "marketCapUsd": 3247416,
        "priceChange24h": 21.51,
        "volume24h": 285253.18,
        "liquidity": 163089.22,
        "logoUrl": "https://cdn.dexscreener.com/cms/images/qxjVI03LToRSxlUo?width=800&height=800&quality=95&format=auto",
        "pairAddress": "BRbvi3YR1RRKoRBk5xCAG1E5urLdyJgRmJixVzD6GfFc"
      }
    ],
    "ai": [
      {
        "name": "DeAgentAI",
        "symbol": "AIA",
        "assetId": "0x53EC33Cd4fA46b9ecED9cA3f6dB626C5FfCd55cC",
        "chain": "bsc",
        "priceUsd": 0.05358,
        "marketCapUsd": 10716221,
        "priceChange24h": -1.36,
        "volume24h": 635648.63,
        "liquidity": 586833.9,
        "logoUrl": null,
        "pairAddress": "0xADEDafd06CC16Dec264Fb02D3f8570E072DAEe35"
      }
    ],
    "pumpfun": [
      {
        "name": "The Pumpfun Historian",
        "symbol": "NARC",
        "assetId": "2A9bscgi4N8gQxpMsR5HdgzN25q5setem8du8TD5pump",
        "chain": "solana",
        "priceUsd": 0.0001472,
        "marketCapUsd": 147130,
        "priceChange24h": 355,
        "volume24h": 705295.21,
        "liquidity": 29647.96,
        "logoUrl": "https://cdn.dexscreener.com/cms/images/7CiilQCDYSACICn9?width=800&height=800&quality=95&format=auto",
        "pairAddress": "CNgYhQVm3mdwNsZeaf9NgnBxf5gWbxsDCrrg4qL48J2A"
      },
      {
        "name": "rex.fun",
        "symbol": "REX",
        "assetId": "CmQJNJ185pjzQoebPbcqZu1kTykHxJbn4gER1Af7pump",
        "chain": "solana",
        "priceUsd": 0.0002672,
        "marketCapUsd": 267222,
        "priceChange24h": 17.94,
        "volume24h": 19301.86,
        "liquidity": 40200.18,
        "logoUrl": "https://cdn.dexscreener.com/cms/images/ZwYnJWecMpyXFYR4?width=800&height=800&quality=95&format=auto",
        "pairAddress": "8XzxTTCfQ49N5awdmtLAoK7MKmZ65AAaTpqryD9M1jL7"
      },
      {
        "name": "The PumpFun Father",
        "symbol": "ALON",
        "assetId": "7XSmrerjGbVi9uVW8qVHfp7SN1GU1vnxHguzUEt1pump",
        "chain": "solana",
        "priceUsd": 0.0005566,
        "marketCapUsd": 556481,
        "priceChange24h": -4.59,
        "volume24h": 22377.46,
        "liquidity": 59094.15,
        "logoUrl": "https://cdn.dexscreener.com/cms/images/arbxwjMvR6A-DfOB?width=800&height=800&quality=95&format=auto",
        "pairAddress": "J7HdS6Hi2HejMLLpkpRerVQHjHiCDYXy4LK18p1zyYVk"
      },
      {
        "name": "Pumpfun Pepe",
        "symbol": "PFP",
        "assetId": "5TfqNKZbn9AnNtzq8bbkyhKgcPGTfNDc9wNzFrTBpump",
        "chain": "solana",
        "priceUsd": 0.0004732,
        "marketCapUsd": 473038,
        "priceChange24h": -8.45,
        "volume24h": 23185.3,
        "liquidity": 98469.98,
        "logoUrl": "https://cdn.dexscreener.com/cms/images/wHcAEnoGnOrQXkai?width=800&height=800&quality=95&format=auto",
        "pairAddress": "GdFCD7L8x1GiudFz1wthNHEb352k3Ni37rSwtJgMgLpT"
      }
    ]
  }
}