{
  "updatedAt": "2026-07-08T15:35:20.970Z",
  "categories": {
    "memes": [],
    "bnb": [
      {
        "name": "Trusty AI",
        "symbol": "Trusty",
        "assetId": "0x65aea108c21439693468FCD542D81C29E8df4444",
        "chain": "bsc",
        "priceUsd": 0.00003963,
        "marketCapUsd": 39633,
        "priceChange24h": 2.4,
        "volume24h": 2019.85,
        "liquidity": 21567.27,
        "logoUrl": "https://cdn.dexscreener.com/cms/images/X-shg1fyEiyjZ92z?width=800&height=800&quality=95&format=auto",
        "pairAddress": "0xe2D86D6dFDE0D428f8F83260b6C7c1e7f16C8ed2",
        "pinned": true
      },
      {
        "name": "Binance Super Cycle",
        "symbol": "BSC",
        "assetId": "0x6331BF8D601f0D7F0d2101772af5137c418c4444",
        "chain": "bsc",
        "priceUsd": 0.0001014,
        "marketCapUsd": 101483,
        "priceChange24h": -11.28,
        "volume24h": 11217.86,
        "liquidity": 52692.57,
        "logoUrl": "https://cdn.dexscreener.com/cms/images/207594269024794d1d015da53f579070e5a481cb8526bebd64cea52c7699e72d?width=800&height=800&quality=95&format=auto",
        "pairAddress": "0xff0A8df8c4A0332E28a4c94EBB3f633944B08a94"
      }
    ],
    "eth": [],
    "sol": [
      {
        "name": "MASON VERSLUIS",
        "symbol": "MASON",
        "assetId": "4gqUH4qMtkZTjeenrtVmcQXKEYg9aBUC8j2kQao2pump",
        "chain": "solana",
        "priceUsd": 0.002273,
        "marketCapUsd": 2273456,
        "priceChange24h": 4250,
        "volume24h": 4560316.65,
        "liquidity": 123057.66,
        "logoUrl": "https://cdn.dexscreener.com/cms/images/9sS3PNgkCBl5xoyU?width=800&height=800&quality=95&format=auto",
        "pairAddress": "6Adx5qhm4iwEE39nik8cAmbb3sjdGSLW7VgPomy2Vqwz"
      },
      {
        "name": "Bull Cupsey",
        "symbol": "BULLSEY",
        "assetId": "7aD86TAvoXPBAkt7HxGsz3MG8UBdDUvcVeBLouVcpump",
        "chain": "solana",
        "priceUsd": 0.001733,
        "marketCapUsd": 1733847,
        "priceChange24h": 3170,
        "volume24h": 7621339.88,
        "liquidity": 111445.28,
        "logoUrl": "https://cdn.dexscreener.com/cms/images/sYVIsnodMfk3qDeX?width=800&height=800&quality=95&format=auto",
        "pairAddress": "6mc6TxdrcKL1MHr8S9KYs55cCHKdzx3aYianaS6AA9Ym"
      },
      {
        "name": "NIGGABULL",
        "symbol": "NIGGABULL",
        "assetId": "77x1fCskDLaiZmm2uZKEhARSCD2B86VaahTkK2Vfpump",
        "chain": "solana",
        "priceUsd": 0.0005694,
        "marketCapUsd": 569419,
        "priceChange24h": 1225,
        "volume24h": 1561106.23,
        "liquidity": 61283.35,
        "logoUrl": "https://cdn.dexscreener.com/cms/images/EFfwoTPIz2eqlIQM?width=800&height=800&quality=95&format=auto",
        "pairAddress": "985nRFKE9yHRwmPVPW7GCje1Jr7WtDdnyzb4QCNZEq15"
      },
      {
        "name": "Robin wif Hood",
        "symbol": "RIF",
        "assetId": "G7zeUXZzTUa8iXeUcW5J8oK9zoK4WY75fzmwFMe5pump",
        "chain": "solana",
        "priceUsd": 0.0001938,
        "marketCapUsd": 184748,
        "priceChange24h": 503,
        "volume24h": 761591.6,
        "liquidity": 33748.75,
        "logoUrl": "https://cdn.dexscreener.com/cms/images/Gq5dY4wi5Dv_s6i4?width=800&height=800&quality=95&format=auto",
        "pairAddress": "PAn7XphfksZCYWTGg6k3NxGjx9zTR91LNQSwQfKE4Qw"
      },
      {
        "name": "Baby Cupsey",
        "symbol": "BabyCupsey",
        "assetId": "Hk8qqvyYU5gfAB5QCZCcJq3gR3TZ8LtvNmA1EM3bpump",
        "chain": "solana",
        "priceUsd": 0.0001787,
        "marketCapUsd": 178740,
        "priceChange24h": 434,
        "volume24h": 1791813.16,
        "liquidity": 34706.63,
        "logoUrl": "https://cdn.dexscreener.com/cms/images/kSIcUbHL2VJn_HcH?width=800&height=800&quality=95&format=auto",
        "pairAddress": "4dtPPur4Cp7eKsn57BS2cNxAY3E98fJTz5KCe8V5juu2"
      },
      {
        "name": "The Orange Bull",
        "symbol": "SAYLOR",
        "assetId": "BGwYnDVe18aj9cozWcKNhiTUwayELULg5rHLGPPdpump",
        "chain": "solana",
        "priceUsd": 0.002484,
        "marketCapUsd": 2478661,
        "priceChange24h": 276,
        "volume24h": 197025.6,
        "liquidity": 117527.26,
        "logoUrl": "https://cdn.dexscreener.com/cms/images/h5IGeYhsSNNLeJuY?width=800&height=800&quality=95&format=auto",
        "pairAddress": "5YoAQPw38JfHSLJ8cmd2zJ7KSjAJbzHtPv1Kx9fJEkZv"
      },
      {
        "name": "CASH DOG",
        "symbol": "CASHDOG",
        "assetId": "8YFpCz4pxkNQxowNDyQrPmDizXQLhFF5xn87oG14pump",
        "chain": "solana",
        "priceUsd": 0.0001581,
        "marketCapUsd": 158147,
        "priceChange24h": 275,
        "volume24h": 1611608.77,
        "liquidity": 32350.39,
        "logoUrl": "https://cdn.dexscreener.com/cms/images/dSd5JGAsJ4LXmvO9?width=800&height=800&quality=95&format=auto",
        "pairAddress": "61qaPD5BiRqSN4i3pPnS8sY8NRGSWXGppLaZuYQx6A87"
      },
      {
        "name": "baby toly wif hat",
        "symbol": "tolywifhat",
        "assetId": "E2ueKQ3EDTTmCkUA17j3KeTb2u6VT91xiyECdKRzpump",
        "chain": "solana",
        "priceUsd": 0.00244,
        "marketCapUsd": 2440610,
        "priceChange24h": 229,
        "volume24h": 5727541.42,
        "liquidity": 144983.9,
        "logoUrl": "https://cdn.dexscreener.com/cms/images/OpJPWh_yKAlsKzfm?width=800&height=800&quality=95&format=auto",
        "pairAddress": "Gdc11VQJFq6isPtw1AvoQoWxNd7Eq3JeTJWh1LTT4qT8"
      },
      {
        "name": "The Whale Monkey",
        "symbol": "$TWM$",
        "assetId": "CS2T1HQRPCXaYR5V3SNDb5ceERwZg1Nb5uuw6Dg5hpsn",
        "chain": "solana",
        "priceUsd": 0.00005506,
        "marketCapUsd": 55062,
        "priceChange24h": 80.98,
        "volume24h": 28331.12,
        "liquidity": 28395.77,
        "logoUrl": null,
        "pairAddress": "5hc8GruCvLQQd8mw85Ai1nV6v1tyuA9a8HMt1quTNA6"
      },
      {
        "name": "NeverZero",
        "symbol": "NEVERZERO",
        "assetId": "7MsJCvDi5t5U3Ya2UAs5bR75VJyVMr2FKdzGmeg2rise",
        "chain": "solana",
        "priceUsd": 0.4368,
        "marketCapUsd": 21580857,
        "priceChange24h": -5.22,
        "volume24h": 17691.69,
        "liquidity": 20133841,
        "logoUrl": "https://cdn.dexscreener.com/cms/images/gvZ36rP-rPGKBvH0?width=800&height=800&quality=95&format=auto",
        "pairAddress": "Dmryq83qiuGuRjd36QkY5Y2cEFZajqrhuXW8kYVG1z2E"
      }
    ],
    "ai": [
      {
        "name": "DeAgentAI",
        "symbol": "AIA",
        "assetId": "0x53EC33Cd4fA46b9ecED9cA3f6dB626C5FfCd55cC",
        "chain": "bsc",
        "priceUsd": 0.05237,
        "marketCapUsd": 10474007,
        "priceChange24h": -0.6,
        "volume24h": 1059786.84,
        "liquidity": 578601.29,
        "logoUrl": null,
        "pairAddress": "0xADEDafd06CC16Dec264Fb02D3f8570E072DAEe35"
      }
    ],
    "pumpfun": [
      {
        "name": "Swindly Sam",
        "symbol": "SWINDLY",
        "assetId": "FuneXM5C1PuUuCuyMn5uoGGDVkMpShSThTsKjSEipump",
        "chain": "solana",
        "priceUsd": 0.000114,
        "marketCapUsd": 114039,
        "priceChange24h": 7682,
        "volume24h": 23148.31,
        "liquidity": 24846.99,
        "logoUrl": "https://cdn.dexscreener.com/cms/images/xAlkM6gRLp9gm8Q5?width=800&height=800&quality=95&format=auto",
        "pairAddress": "Gk4uBaQibX6roMXiCHcvAGbjLQKBiZYR81CwVf2DY76G"
      },
      {
        "name": "rex.fun",
        "symbol": "REX",
        "assetId": "CmQJNJ185pjzQoebPbcqZu1kTykHxJbn4gER1Af7pump",
        "chain": "solana",
        "priceUsd": 0.0002343,
        "marketCapUsd": 234366,
        "priceChange24h": 33.79,
        "volume24h": 25870.13,
        "liquidity": 37246.6,
        "logoUrl": "https://cdn.dexscreener.com/cms/images/ZwYnJWecMpyXFYR4?width=800&height=800&quality=95&format=auto",
        "pairAddress": "8XzxTTCfQ49N5awdmtLAoK7MKmZ65AAaTpqryD9M1jL7"
      },
      {
        "name": "Pumpfun Pepe",
        "symbol": "PFP",
        "assetId": "5TfqNKZbn9AnNtzq8bbkyhKgcPGTfNDc9wNzFrTBpump",
        "chain": "solana",
        "priceUsd": 0.0004926,
        "marketCapUsd": 492470,
        "priceChange24h": 25.48,
        "volume24h": 932251.74,
        "liquidity": 99521.77,
        "logoUrl": "https://cdn.dexscreener.com/cms/images/wHcAEnoGnOrQXkai?width=800&height=800&quality=95&format=auto",
        "pairAddress": "GdFCD7L8x1GiudFz1wthNHEb352k3Ni37rSwtJgMgLpT"
      },
      {
        "name": "PumpFunFloki",
        "symbol": "PFF",
        "assetId": "DPgo26tLZXdNfB24ahP2LTXsxSPxvxPq7takvavppump",
        "chain": "solana",
        "priceUsd": 0.00009412,
        "marketCapUsd": 89357,
        "priceChange24h": -5.42,
        "volume24h": 5997.69,
        "liquidity": 25363.87,
        "logoUrl": "https://cdn.dexscreener.com/cms/images/012c2470a25c424d80a96a8a6c6475ac8a3190c33eb56e98830968f9f35b369e?width=800&height=800&quality=95&format=auto",
        "pairAddress": "EEb1xU5Dp9iz573SpXXSUBjVPdUXdr7knPbrryNfL91z"
      },
      {
        "name": "The PumpFun Father",
        "symbol": "ALON",
        "assetId": "7XSmrerjGbVi9uVW8qVHfp7SN1GU1vnxHguzUEt1pump",
        "chain": "solana",
        "priceUsd": 0.0005745,
        "marketCapUsd": 574347,
        "priceChange24h": -35.72,
        "volume24h": 69318.37,
        "liquidity": 59302.26,
        "logoUrl": "https://cdn.dexscreener.com/cms/images/arbxwjMvR6A-DfOB?width=800&height=800&quality=95&format=auto",
        "pairAddress": "J7HdS6Hi2HejMLLpkpRerVQHjHiCDYXy4LK18p1zyYVk"
      },
      {
        "name": "The Pumpfun Rats",
        "symbol": "RATS",
        "assetId": "EX19gh6n6CUsXgionv5vtNQZPC24UzJKQhU8uBnnpump",
        "chain": "solana",
        "priceUsd": 0.00008054,
        "marketCapUsd": 80535,
        "priceChange24h": -57.43,
        "volume24h": 98904.38,
        "liquidity": 21184.27,
        "logoUrl": null,
        "pairAddress": "8CHpgnyuP9nTJMdirMn7P2uF77f3hiyLXyxhzoDPR64m"
      }
    ]
  }
}